bot_gpt/__init__.py
bot_gpt/alerts.json
bot_gpt/cipher.py
bot_gpt/disclaimer.txt
bot_gpt/help_admin.txt
bot_gpt/help_dev.txt
bot_gpt/help_user.txt
bot_gpt/setting.json
telegram_bot_gpt-0.3.0.dist-info/LICENSE
telegram_bot_gpt-0.3.0.dist-info/METADATA
telegram_bot_gpt-0.3.0.dist-info/WHEEL
telegram_bot_gpt-0.3.0.dist-info/top_level.txt
telegram_bot_gpt-0.3.0.dist-info/RECORD
