Metadata-Version: 2.1
Name: telegram-bot-gpt
Version: 0.3.0
Summary: A simple interface for OpenAI GPT-3 and GPT-4 using Telegram bots
Author: Nugroho Fredivianus
Author-email: nuggfr@gmail.com
License: MIT
Keywords: chatbot,artificial intelligence,gpt transformers,nlp
Classifier: Programming Language :: Python :: 3
Classifier: Topic :: Scientific/Engineering :: Artificial Intelligence
Classifier: License :: OSI Approved :: MIT License
Classifier: Operating System :: OS Independent
License-File: LICENSE
Requires-Dist: python-telegram-bot (==13.*)
Requires-Dist: openai (==0.27.0)
